aav.upcoming_games-0.1.0.dist-info/DESCRIPTION.rst
aav.upcoming_games-0.1.0.dist-info/METADATA
aav.upcoming_games-0.1.0.dist-info/RECORD
aav.upcoming_games-0.1.0.dist-info/WHEEL
aav.upcoming_games-0.1.0.dist-info/entry_points.txt
aav.upcoming_games-0.1.0.dist-info/metadata.json
aav.upcoming_games-0.1.0.dist-info/top_level.txt
upcoming_games/__init__.py
