Metadata-Version: 2.0
Name: aav.upcoming-games
Version: 0.1.0
Summary: Reddit bot to provide updates for video games.
Home-page: https://github.com/aav-bots/upcoming-games
Author: aav-bots
Author-email: UNKNOWN
License: MIT
Keywords: aav upcoming games reddit bot
Platform: UNKNOWN
Classifier: Development Status :: 4 - Beta
Classifier: Intended Audience :: Developers
Classifier: Intended Audience :: End Users/Desktop
Classifier: License :: OSI Approved :: MIT License
Classifier: Operating System :: OS Independent
Classifier: Natural Language :: English
Classifier: Programming Language :: Python :: 3.6
Requires-Python: >=3.6
Requires-Dist: praw
Requires-Dist: requests
Requires-Dist: ruamel.yaml
Requires-Dist: parsedatetime
Requires-Dist: beautifulsoup4
